jdict/__init__.py
jdict-1.0.0.dist-info/LICENSE
jdict-1.0.0.dist-info/METADATA
jdict-1.0.0.dist-info/WHEEL
jdict-1.0.0.dist-info/top_level.txt
jdict-1.0.0.dist-info/RECORD
