Metadata-Version: 2.1
Name: jdict
Version: 1.0.0
Summary: Dictionary extended with convenience methods that depend heavily on dictionaries being ordered by insertion order.
Home-page: https://github.com/jonathangjertsen/jdict
Author: Jonathan Reichelt Gjertsen
Author-email: jonath.re@gmail.com
License: MIT
Platform: UNKNOWN
